tokenregex
