Metadata-Version: 1.1
Name: tokenregex
Version: 0.1.13
Summary: NLP at your fingertips
Home-page: https://github.com/ramtinms/tokenregex
Author: Ramtin Seraj
Author-email: mehdizadeh.ramtin@gmail.com
License: UNKNOWN
Download-URL: https://github.com/ramtinms/tokenregex/tarball/0.1
Keywords: natural language processing,nlp,regex,tokenizer
Platform: UNKNOWN
Classifier: Intended Audience :: Information Technology
Classifier: Intended Audience :: Science/Research
Classifier: Topic :: Scientific/Engineering
Classifier: Topic :: Scientific/Engineering :: Artificial Intelligence
Classifier: Topic :: Scientific/Engineering :: Human Machine Interfaces
Classifier: Topic :: Scientific/Engineering :: Information Analysis
Classifier: Topic :: Text Processing
Classifier: Topic :: Text Processing :: Filters
Classifier: Topic :: Text Processing :: General
Classifier: Topic :: Text Processing :: Indexing
Classifier: Topic :: Text Processing :: Linguistic
